nimrodel/__init__.py
nimrodel/_api.py
nimrodel/_apifunction.py
nimrodel/_apiobject.py
nimrodel/_apirest.py
nimrodel/_misc.py
nimrodel/output/__init__.py
nimrodel/output/json.py
nimrodel/output/xml.py
nimrodel/res/apiexplorer.jinja
nimrodel/res/apiexplorer.pyhp
nimrodel/res/apiexplorer_endpoint.jinja
nimrodel/res/apiexplorer_endpoint.pyhp
nimrodel/res/apiexplorer_object.jinja
nimrodel/res/apiexplorer_object.pyhp
nimrodel/res/apiexplorer_rest.jinja
nimrodel/res/apiexplorer_rest.pyhp
nimrodel-0.8.0.dist-info/LICENSE
nimrodel-0.8.0.dist-info/WHEEL
nimrodel-0.8.0.dist-info/METADATA
nimrodel-0.8.0.dist-info/RECORD
